django_hunger2/__init__.py
django_hunger2/admin.py
django_hunger2/email.py
django_hunger2/forms.py
django_hunger2/middleware.py
django_hunger2/models.py
django_hunger2/urls.py
django_hunger2/utils.py
django_hunger2/views.py
django_hunger2/migrations/0001_initial.py
django_hunger2/migrations/__init__.py
django_hunger2-2.2.0.dist-info/LICENSE
django_hunger2-2.2.0.dist-info/METADATA
django_hunger2-2.2.0.dist-info/WHEEL
django_hunger2-2.2.0.dist-info/top_level.txt
django_hunger2-2.2.0.dist-info/RECORD
