Metadata-Version: 2.1
Name: django-hunger2
Version: 2.2.0
Summary: A Django app to manage a private beta phase.
Home-page: https://github.com/joshuakarjala/django-django_hunger2/
Author: Joshua Karjala-Svenden
Author-email: joshua@fluxuries.com
License: MIT
Platform: any
Classifier: Development Status :: 5 - Production/Stable
Classifier: Intended Audience :: Developers
Classifier: License :: OSI Approved :: MIT License
Classifier: Operating System :: OS Independent
Classifier: Programming Language :: Python
Classifier: Topic :: Software Development :: Libraries :: Python Modules
Classifier: Framework :: Django
Provides-Extra: test
Requires-Dist: Django (>=2.0); extra == 'test'
